{
    "tunings": [
        {
            "name": "Standard",
            "notes": [
                "E2 ",
                "A2 ",
                "D3 ",
                "G3 ",
                "B3 ",
                "E4 "
            ]
        },
        {
            "name": "Drop D",
            "notes": [
                "D2 ",
                "A2 ",
                "D3 ",
                "G3 ",
                "B3 ",
                "E4 "
            ]
        },
        {
            "name": "Drop C",
            "notes": [
                "C2 ",
                "G2 ",
                "C3 ",
                "F3 ",
                "A3 ",
                "D4 "
            ]
        },
        {
            "name": "Open G",
            "notes": [
                "D2 ",
                "G2 ",
                "D3 ",
                "G3 ",
                "B3 ",
                "D4 "
            ]
        },
        {
            "name": "Half Step Down",
            "notes": [
                "D#2",
                "G#2",
                "C#3",
                "F#3",
                "A#3",
                "D#4"
            ]
        }
    ],
    "color_themes": [
        {
            "name": "Nord",
            "primary": "#88C0D0",
            "secondary": "#A3BE8C",
            "tertiary": "#EBCB8B"
        },
        {
            "name": "Catppuccin",
            "primary": "#89B4FA",
            "secondary": "#F38BA8",
            "tertiary": "#FAB387"
        },
        {
            "name": "Gruvbox",
            "primary": "#D79921",
            "secondary": "#B8BB26",
            "tertiary": "#A89984"
        },
        {
            "name": "Tokyo Night",
            "primary": "#7AA2F7",
            "secondary": "#0DB9D7",
            "tertiary": "#BB9AF7"
        },
        {
            "name": "Dracula",
            "primary": "#BD93F9",
            "secondary": "#50FA7B",
            "tertiary": "#FF79C6"
        }
    ],
    "border_styles": [
        "None",
        "Normal",
        "Rounded",
        "Double",
        "Block",
        "Inner Block",
        "Outer Block",
        "Thick",
        "Ascii"
    ]
}
